{"updated":"2026-07-24T16:49:43+00:00","league":"Runes of Aldur","primary":"divine","secondary":"chaos","rates":{"exalted":478.4,"chaos":9.14},"currencies":[{"id":"greater-orb-of-transmutation","name":"Greater Orb of Transmutation","divine":0.001111,"volume":4.0,"change7d":-91.84},{"id":"divine","name":"Divine Orb","divine":1,"volume":76110,"change7d":28.17},{"id":"chaos","name":"Chaos Orb","divine":0.1095,"volume":76110,"change7d":-21.98},{"id":"vaal-armourers-infuser","name":"Vaal Armourer's Infuser","divine":0.937,"volume":1634,"change7d":-29.58},{"id":"whetstone","name":"Blacksmith's Whetstone","divine":0.001635,"volume":11.7,"change7d":-12.18},{"id":"exalted","name":"Exalted Orb","divine":0.00209,"volume":7397,"change7d":-5.51},{"id":"orb-of-extraction","name":"Orb of Extraction","divine":1.1,"volume":140.5,"change7d":-10.12},{"id":"etcher","name":"Arcanist's Etcher","divine":0.00732,"volume":22.72,"change7d":-10.87},{"id":"vaal-arcanists-infuser","name":"Vaal Arcanist's Infuser","divine":0.02272,"volume":6.49,"change7d":70.92},{"id":"wisdom","name":"Scroll of Wisdom","divine":2.147e-05,"volume":0.708,"change7d":-27.2},{"id":"aug","name":"Orb of Augmentation","divine":0.0007461,"volume":3.67,"change7d":-7.85},{"id":"yaomacs-orb-of-sacrifice","name":"Yaomac's Orb of Sacrifice","divine":0.025,"volume":0.1084,"change7d":47.75},{"id":"kopecs-orb-of-sacrifice","name":"Kopec's Orb of Sacrifice","divine":0.1347,"volume":2.15,"change7d":44.23},{"id":"vaal-cultivation-orb","name":"Vaal Cultivation Orb","divine":1.61,"volume":1235,"change7d":-38.14},{"id":"vaal","name":"Vaal Orb","divine":0.006473,"volume":276.5,"change7d":-15.99},{"id":"alch","name":"Orb of Alchemy","divine":0.001716,"volume":43.33,"change7d":-22.6},{"id":"chance","name":"Orb of Chance","divine":0.01555,"volume":82.67,"change7d":14.69},{"id":"perfect-exalted-orb","name":"Perfect Exalted Orb","divine":2.69,"volume":9158,"change7d":-7.91},{"id":"gcp","name":"Gemcutter's Prism","divine":0.01072,"volume":87.5,"change7d":-48.42},{"id":"regal","name":"Regal Orb","divine":0.0007095,"volume":6.69,"change7d":-32.11},{"id":"perfect-regal-orb","name":"Perfect Regal Orb","divine":0.05432,"volume":96.0,"change7d":-36.38},{"id":"yuguls-orb-of-sacrifice","name":"Yugul's Orb of Sacrifice","divine":0.05063,"volume":0.3798,"change7d":270.3},{"id":"kamasas-orb-of-sacrifice","name":"Kamasa's Orb of Sacrifice","divine":0.4051,"volume":5.33,"change7d":118.1},{"id":"transmute","name":"Orb of Transmutation","divine":0.0004881,"volume":2.33,"change7d":-10.59},{"id":"perfect-chaos-orb","name":"Perfect Chaos Orb","divine":5.82,"volume":15178,"change7d":1.24},{"id":"fracturing-orb","name":"Fracturing Orb","divine":9.04,"volume":9894,"change7d":-15.5},{"id":"perfect-jewellers-orb","name":"Perfect Jeweller's Orb","divine":0.2999,"volume":876.0,"change7d":-19.43},{"id":"ancient-infuser","name":"Ancient Infuser","divine":0.3182,"volume":148.7,"change7d":-14.85},{"id":"bauble","name":"Glassblower's Bauble","divine":0.003388,"volume":6.77,"change7d":-24.64},{"id":"artificers","name":"Artificer's Orb","divine":0.004206,"volume":8.06,"change7d":-23.07},{"id":"greater-chaos-orb","name":"Greater Chaos Orb","divine":0.332,"volume":4347,"change7d":-21.16},{"id":"perfect-orb-of-transmutation","name":"Perfect Orb of Transmutation","divine":0.01504,"volume":35.67,"change7d":6.92},{"id":"vaal-catalysing-infuser","name":"Vaal Catalysing Infuser","divine":5.13,"volume":1899,"change7d":31.63},{"id":"architects-orb","name":"Architect's Orb","divine":4.72,"volume":3878,"change7d":8.38},{"id":"cryptic-key","name":"Cryptic Key","divine":0.6,"volume":43.8,"change7d":53.05},{"id":"vaal-blacksmiths-infuser","name":"Vaal Blacksmith's Infuser","divine":0.2309,"volume":226.7,"change7d":-0.34},{"id":"greater-exalted-orb","name":"Greater Exalted Orb","divine":0.01158,"volume":102.3,"change7d":-17.46},{"id":"crystallised-corruption","name":"Crystallised Corruption","divine":2.69,"volume":1535,"change7d":-5.2},{"id":"greater-orb-of-augmentation","name":"Greater Orb of Augmentation","divine":0.000231,"volume":1.27,"change7d":-52.48},{"id":"mirror","name":"Mirror of Kalandra","divine":4863,"volume":146699,"change7d":-3.92},{"id":"artificers-shard","name":"Artificer's Shard","divine":0.002314,"volume":0.0108,"change7d":25.38},{"id":"greater-regal-orb","name":"Greater Regal Orb","divine":0.003224,"volume":5.52,"change7d":-59.35},{"id":"core-destabiliser","name":"Core Destabiliser","divine":3.77,"volume":1939,"change7d":-27.26},{"id":"hinekoras-lock","name":"Hinekora's Lock","divine":1125,"volume":37109,"change7d":-10.78},{"id":"chance-shard","name":"Chance Shard","divine":0.001481,"volume":0.01777,"change7d":-52.83},{"id":"perfect-orb-of-augmentation","name":"Perfect Orb of Augmentation","divine":0.07765,"volume":773.5,"change7d":-14.68},{"id":"lesser-jewellers-orb","name":"Lesser Jeweller's Orb","divine":6.213e-05,"volume":0.005923,"change7d":-24.67},{"id":"transmutation-shard","name":"Transmutation Shard","divine":0.0209,"volume":0.003484,"change7d":900},{"id":"scrap","name":"Armourer's Scrap","divine":0.00624,"volume":139.8,"change7d":-19.37},{"id":"vaal-siphoner","name":"Vaal Siphoner","divine":0.0006783,"volume":0.03832,"change7d":62.01},{"id":"greater-jewellers-orb","name":"Greater Jeweller's Orb","divine":0.001386,"volume":1.42,"change7d":-31.4},{"id":"annul","name":"Orb of Annulment","divine":0.4634,"volume":9740,"change7d":-35.41}]}
