{"updated":"2026-07-14T20:42:52+00:00","league":"Runes of Aldur","primary":"divine","secondary":"chaos","rates":{"exalted":447.4,"chaos":7.58},"currencies":[{"id":"chaos","name":"Chaos Orb","divine":0.132,"volume":202181,"change7d":13.52},{"id":"bauble","name":"Glassblower's Bauble","divine":0.003993,"volume":16.59,"change7d":91.36},{"id":"greater-orb-of-transmutation","name":"Greater Orb of Transmutation","divine":0.0001515,"volume":1.16,"change7d":-82.49},{"id":"divine","name":"Divine Orb","divine":1,"volume":202181,"change7d":-11.91},{"id":"crystallised-corruption","name":"Crystallised Corruption","divine":2.87,"volume":2819,"change7d":-16.74},{"id":"exalted","name":"Exalted Orb","divine":0.002235,"volume":18194,"change7d":36.99},{"id":"vaal-armourers-infuser","name":"Vaal Armourer's Infuser","divine":0.9179,"volume":3221,"change7d":111.0},{"id":"whetstone","name":"Blacksmith's Whetstone","divine":0.00153,"volume":20.76,"change7d":15.08},{"id":"orb-of-extraction","name":"Orb of Extraction","divine":0.7211,"volume":116.2,"change7d":-5.54},{"id":"greater-exalted-orb","name":"Greater Exalted Orb","divine":0.008458,"volume":181.0,"change7d":11.72},{"id":"greater-orb-of-augmentation","name":"Greater Orb of Augmentation","divine":0.0004434,"volume":6.1,"change7d":-7.14},{"id":"regal","name":"Regal Orb","divine":0.001113,"volume":15.45,"change7d":-30.27},{"id":"etcher","name":"Arcanist's Etcher","divine":0.01194,"volume":133.8,"change7d":12.64},{"id":"vaal-arcanists-infuser","name":"Vaal Arcanist's Infuser","divine":0.02184,"volume":19.4,"change7d":456.9},{"id":"wisdom","name":"Scroll of Wisdom","divine":9.287e-05,"volume":3.52,"change7d":-30.22},{"id":"perfect-jewellers-orb","name":"Perfect Jeweller's Orb","divine":0.309,"volume":1939,"change7d":12.15},{"id":"aug","name":"Orb of Augmentation","divine":0.0008335,"volume":13.67,"change7d":-9.16},{"id":"yaomacs-orb-of-sacrifice","name":"Yaomac's Orb of Sacrifice","divine":0.02499,"volume":0.6039,"change7d":-55.24},{"id":"vaal-siphoner","name":"Vaal Siphoner","divine":0.0002293,"volume":0.00298,"change7d":-2.83},{"id":"kopecs-orb-of-sacrifice","name":"Kopec's Orb of Sacrifice","divine":0.32,"volume":9.33,"change7d":-36.29},{"id":"vaal-cultivation-orb","name":"Vaal Cultivation Orb","divine":3.16,"volume":5474,"change7d":-23.51},{"id":"vaal","name":"Vaal Orb","divine":0.007113,"volume":538.3,"change7d":-2.63},{"id":"alch","name":"Orb of Alchemy","divine":0.00187,"volume":81.33,"change7d":-19.91},{"id":"vaal-catalysing-infuser","name":"Vaal Catalysing Infuser","divine":4.71,"volume":3864,"change7d":93.14},{"id":"chance","name":"Orb of Chance","divine":0.01051,"volume":107.3,"change7d":-21.57},{"id":"greater-regal-orb","name":"Greater Regal Orb","divine":0.006926,"volume":24.5,"change7d":-27.97},{"id":"perfect-exalted-orb","name":"Perfect Exalted Orb","divine":2.92,"volume":20345,"change7d":-5.78},{"id":"gcp","name":"Gemcutter's Prism","divine":0.01435,"volume":211.5,"change7d":27.58},{"id":"fracturing-orb","name":"Fracturing Orb","divine":12.12,"volume":29045,"change7d":3.95},{"id":"yuguls-orb-of-sacrifice","name":"Yugul's Orb of Sacrifice","divine":0.02669,"volume":0.2179,"change7d":-25.73},{"id":"kamasas-orb-of-sacrifice","name":"Kamasa's Orb of Sacrifice","divine":0.05066,"volume":1.27,"change7d":-76.96},{"id":"ancient-infuser","name":"Ancient Infuser","divine":0.3525,"volume":370.2,"change7d":53.51},{"id":"perfect-regal-orb","name":"Perfect Regal Orb","divine":0.06962,"volume":327.2,"change7d":-0.83},{"id":"core-destabiliser","name":"Core Destabiliser","divine":4.79,"volume":6966,"change7d":14.75},{"id":"transmute","name":"Orb of Transmutation","divine":0.0003981,"volume":4.92,"change7d":-45.04},{"id":"scrap","name":"Armourer's Scrap","divine":0.004066,"volume":170.3,"change7d":56.3},{"id":"perfect-chaos-orb","name":"Perfect Chaos Orb","divine":6.09,"volume":31429,"change7d":-31.55},{"id":"vaal-blacksmiths-infuser","name":"Vaal Blacksmith's Infuser","divine":0.2486,"volume":393.5,"change7d":157.3},{"id":"artificers","name":"Artificer's Orb","divine":0.001863,"volume":6.55,"change7d":-37.22},{"id":"greater-jewellers-orb","name":"Greater Jeweller's Orb","divine":0.003474,"volume":5.41,"change7d":20.54},{"id":"greater-chaos-orb","name":"Greater Chaos Orb","divine":0.3949,"volume":10868,"change7d":12.37},{"id":"perfect-orb-of-transmutation","name":"Perfect Orb of Transmutation","divine":0.01401,"volume":88.5,"change7d":-2.02},{"id":"architects-orb","name":"Architect's Orb","divine":4.47,"volume":5943,"change7d":0.23},{"id":"perfect-orb-of-augmentation","name":"Perfect Orb of Augmentation","divine":0.05497,"volume":1061,"change7d":17.96},{"id":"cryptic-key","name":"Cryptic Key","divine":0.3886,"volume":54.67,"change7d":-56.84},{"id":"lesser-jewellers-orb","name":"Lesser Jeweller's Orb","divine":0.003982,"volume":3.33,"change7d":62.39},{"id":"artificers-shard","name":"Artificer's Shard","divine":0.0007946,"volume":0.02794,"change7d":-79.28},{"id":"regal-shard","name":"Regal Shard","divine":0.0008941,"volume":0.0007451,"change7d":-83.16},{"id":"annul","name":"Orb of Annulment","divine":0.8043,"volume":32336,"change7d":-4.11},{"id":"chance-shard","name":"Chance Shard","divine":0.001947,"volume":0.04024,"change7d":-36.48},{"id":"mirror","name":"Mirror of Kalandra","divine":5374,"volume":226598,"change7d":-23.52},{"id":"hinekoras-lock","name":"Hinekora's Lock","divine":1269,"volume":116736,"change7d":-18.0},{"id":"transmutation-shard","name":"Transmutation Shard","divine":0.008941,"volume":0.004471,"change7d":90.48}]}
