{"updated":"2026-07-15T07:30:50+00:00","league":"Runes of Aldur","primary":"divine","secondary":"chaos","rates":{"exalted":424.3,"chaos":7.36},"currencies":[{"id":"chaos","name":"Chaos Orb","divine":0.1358,"volume":115618,"change7d":12.13},{"id":"bauble","name":"Glassblower's Bauble","divine":0.00346,"volume":10.14,"change7d":107.8},{"id":"exalted","name":"Exalted Orb","divine":0.002357,"volume":12460,"change7d":41.18},{"id":"artificers-shard","name":"Artificer's Shard","divine":0.0003928,"volume":0.0003928,"change7d":-92.07},{"id":"greater-orb-of-transmutation","name":"Greater Orb of Transmutation","divine":0.0004594,"volume":2.34,"change7d":66.26},{"id":"divine","name":"Divine Orb","divine":1,"volume":115618,"change7d":-10.83},{"id":"crystallised-corruption","name":"Crystallised Corruption","divine":2.88,"volume":1772,"change7d":-25.04},{"id":"vaal-armourers-infuser","name":"Vaal Armourer's Infuser","divine":0.992,"volume":2382,"change7d":60.89},{"id":"whetstone","name":"Blacksmith's Whetstone","divine":0.002213,"volume":22.7,"change7d":157.7},{"id":"orb-of-extraction","name":"Orb of Extraction","divine":0.6938,"volume":67.99,"change7d":-26.48},{"id":"greater-exalted-orb","name":"Greater Exalted Orb","divine":0.009078,"volume":114.7,"change7d":18.0},{"id":"greater-orb-of-augmentation","name":"Greater Orb of Augmentation","divine":0.0004242,"volume":3.16,"change7d":4.13},{"id":"regal","name":"Regal Orb","divine":0.00167,"volume":12.83,"change7d":-2.43},{"id":"etcher","name":"Arcanist's Etcher","divine":0.01063,"volume":58.67,"change7d":3.11},{"id":"vaal-arcanists-infuser","name":"Vaal Arcanist's Infuser","divine":0.02923,"volume":7.08,"change7d":324.1},{"id":"wisdom","name":"Scroll of Wisdom","divine":4.471e-05,"volume":2.19,"change7d":-70.57},{"id":"perfect-jewellers-orb","name":"Perfect Jeweller's Orb","divine":0.3062,"volume":1060,"change7d":12.88},{"id":"aug","name":"Orb of Augmentation","divine":0.0008246,"volume":7.67,"change7d":-3.57},{"id":"yaomacs-orb-of-sacrifice","name":"Yaomac's Orb of Sacrifice","divine":0.1567,"volume":5.67,"change7d":-40.09},{"id":"kopecs-orb-of-sacrifice","name":"Kopec's Orb of Sacrifice","divine":0.1049,"volume":1.71,"change7d":-60.86},{"id":"vaal-cultivation-orb","name":"Vaal Cultivation Orb","divine":2.98,"volume":2010,"change7d":-33.13},{"id":"vaal","name":"Vaal Orb","divine":0.008257,"volume":263.5,"change7d":21.89},{"id":"alch","name":"Orb of Alchemy","divine":0.001785,"volume":50.17,"change7d":-16.48},{"id":"vaal-catalysing-infuser","name":"Vaal Catalysing Infuser","divine":4.58,"volume":2214,"change7d":63.61},{"id":"chance","name":"Orb of Chance","divine":0.01089,"volume":68.5,"change7d":9.35},{"id":"greater-regal-orb","name":"Greater Regal Orb","divine":0.00898,"volume":23.5,"change7d":5.92},{"id":"perfect-exalted-orb","name":"Perfect Exalted Orb","divine":3.0,"volume":13143,"change7d":-9.73},{"id":"gcp","name":"Gemcutter's Prism","divine":0.02375,"volume":209.7,"change7d":206.4},{"id":"fracturing-orb","name":"Fracturing Orb","divine":12.08,"volume":16715,"change7d":-10.29},{"id":"yuguls-orb-of-sacrifice","name":"Yugul's Orb of Sacrifice","divine":0.04762,"volume":0.6667,"change7d":-85.71},{"id":"kamasas-orb-of-sacrifice","name":"Kamasa's Orb of Sacrifice","divine":0.2593,"volume":7.0,"change7d":-24.77},{"id":"ancient-infuser","name":"Ancient Infuser","divine":0.7028,"volume":271.2,"change7d":202.2},{"id":"perfect-regal-orb","name":"Perfect Regal Orb","divine":0.07418,"volume":194.5,"change7d":27.28},{"id":"core-destabiliser","name":"Core Destabiliser","divine":5.31,"volume":5231,"change7d":17.49},{"id":"transmute","name":"Orb of Transmutation","divine":0.0005445,"volume":4.17,"change7d":-29.34},{"id":"scrap","name":"Armourer's Scrap","divine":0.003624,"volume":88.32,"change7d":83.96},{"id":"perfect-chaos-orb","name":"Perfect Chaos Orb","divine":6.33,"volume":20144,"change7d":-25.32},{"id":"vaal-blacksmiths-infuser","name":"Vaal Blacksmith's Infuser","divine":0.2374,"volume":191.2,"change7d":83.94},{"id":"vaal-siphoner","name":"Vaal Siphoner","divine":0.04,"volume":0.5,"change7d":-12.0},{"id":"artificers","name":"Artificer's Orb","divine":0.004186,"volume":10.83,"change7d":-26.35},{"id":"greater-jewellers-orb","name":"Greater Jeweller's Orb","divine":0.003174,"volume":3.35,"change7d":16.49},{"id":"greater-chaos-orb","name":"Greater Chaos Orb","divine":0.4092,"volume":5975,"change7d":13.05},{"id":"perfect-orb-of-transmutation","name":"Perfect Orb of Transmutation","divine":0.01488,"volume":48.0,"change7d":-0.69},{"id":"architects-orb","name":"Architect's Orb","divine":4.44,"volume":3664,"change7d":-9.41},{"id":"perfect-orb-of-augmentation","name":"Perfect Orb of Augmentation","divine":0.05542,"volume":642.0,"change7d":33.82},{"id":"cryptic-key","name":"Cryptic Key","divine":0.3406,"volume":26.91,"change7d":-64.21},{"id":"lesser-jewellers-orb","name":"Lesser Jeweller's Orb","divine":3.641e-05,"volume":0.03536,"change7d":-60.52},{"id":"regal-shard","name":"Regal Shard","divine":0.002357,"volume":0.02828,"change7d":-42.0},{"id":"annul","name":"Orb of Annulment","divine":0.805,"volume":17998,"change7d":-9.62},{"id":"chance-shard","name":"Chance Shard","divine":0.001832,"volume":0.07268,"change7d":-75.01},{"id":"mirror","name":"Mirror of Kalandra","divine":5329,"volume":146554,"change7d":-21.99},{"id":"hinekoras-lock","name":"Hinekora's Lock","divine":1302,"volume":67728,"change7d":-16.62}]}
