{"updated":"2026-07-22T14:16:45+00:00","league":"Runes of Aldur","primary":"divine","secondary":"chaos","rates":{"exalted":423.6,"chaos":7.61},"currencies":[{"id":"greater-orb-of-transmutation","name":"Greater Orb of Transmutation","divine":0.0003163,"volume":1.45,"change7d":13.22},{"id":"divine","name":"Divine Orb","divine":1,"volume":100610,"change7d":3.95},{"id":"chaos","name":"Chaos Orb","divine":0.1315,"volume":100610,"change7d":-3.81},{"id":"vaal-armourers-infuser","name":"Vaal Armourer's Infuser","divine":0.866,"volume":1382,"change7d":-8.94},{"id":"whetstone","name":"Blacksmith's Whetstone","divine":0.001524,"volume":11.34,"change7d":7.28},{"id":"exalted","name":"Exalted Orb","divine":0.00236,"volume":9895,"change7d":6.34},{"id":"orb-of-extraction","name":"Orb of Extraction","divine":1.11,"volume":144.8,"change7d":29.8},{"id":"etcher","name":"Arcanist's Etcher","divine":0.009555,"volume":54.17,"change7d":2.99},{"id":"vaal-arcanists-infuser","name":"Vaal Arcanist's Infuser","divine":0.006215,"volume":1.52,"change7d":-73.31},{"id":"wisdom","name":"Scroll of Wisdom","divine":3.312e-05,"volume":0.7294,"change7d":-13.7},{"id":"aug","name":"Orb of Augmentation","divine":0.0005915,"volume":5.27,"change7d":30.87},{"id":"yaomacs-orb-of-sacrifice","name":"Yaomac's Orb of Sacrifice","divine":0.04822,"volume":0.9804,"change7d":14.43},{"id":"kopecs-orb-of-sacrifice","name":"Kopec's Orb of Sacrifice","divine":0.1583,"volume":3.17,"change7d":-51.22},{"id":"vaal-cultivation-orb","name":"Vaal Cultivation Orb","divine":1.59,"volume":1185,"change7d":-48.52},{"id":"vaal","name":"Vaal Orb","divine":0.007444,"volume":380.0,"change7d":7.61},{"id":"alch","name":"Orb of Alchemy","divine":0.002235,"volume":78.17,"change7d":22.22},{"id":"chance","name":"Orb of Chance","divine":0.01426,"volume":61.67,"change7d":41.57},{"id":"perfect-exalted-orb","name":"Perfect Exalted Orb","divine":2.84,"volume":10311,"change7d":-3.24},{"id":"gcp","name":"Gemcutter's Prism","divine":0.01377,"volume":138.2,"change7d":21.88},{"id":"regal","name":"Regal Orb","divine":0.001046,"volume":9.93,"change7d":-21.43},{"id":"perfect-regal-orb","name":"Perfect Regal Orb","divine":0.07938,"volume":164.7,"change7d":5.6},{"id":"yuguls-orb-of-sacrifice","name":"Yugul's Orb of Sacrifice","divine":0.1307,"volume":3.83,"change7d":174.4},{"id":"kamasas-orb-of-sacrifice","name":"Kamasa's Orb of Sacrifice","divine":0.6265,"volume":26.83,"change7d":70.85},{"id":"transmute","name":"Orb of Transmutation","divine":0.0003731,"volume":1.97,"change7d":12.79},{"id":"perfect-chaos-orb","name":"Perfect Chaos Orb","divine":5.85,"volume":13455,"change7d":-10.2},{"id":"fracturing-orb","name":"Fracturing Orb","divine":11.2,"volume":13351,"change7d":-4.61},{"id":"perfect-jewellers-orb","name":"Perfect Jeweller's Orb","divine":0.3509,"volume":1291,"change7d":13.49},{"id":"ancient-infuser","name":"Ancient Infuser","divine":0.3324,"volume":133.0,"change7d":-44.9},{"id":"bauble","name":"Glassblower's Bauble","divine":0.003876,"volume":7.3,"change7d":12.78},{"id":"artificers","name":"Artificer's Orb","divine":0.001309,"volume":2.47,"change7d":-54.61},{"id":"greater-chaos-orb","name":"Greater Chaos Orb","divine":0.3931,"volume":5144,"change7d":-3.82},{"id":"perfect-orb-of-transmutation","name":"Perfect Orb of Transmutation","divine":0.01537,"volume":47.67,"change7d":13.99},{"id":"vaal-catalysing-infuser","name":"Vaal Catalysing Infuser","divine":3.58,"volume":1596,"change7d":-17.61},{"id":"architects-orb","name":"Architect's Orb","divine":4.6,"volume":3965,"change7d":2.46},{"id":"cryptic-key","name":"Cryptic Key","divine":0.6605,"volume":40.18,"change7d":102.0},{"id":"regal-shard","name":"Regal Shard","divine":0.0001749,"volume":0.0007868,"change7d":-85.19},{"id":"vaal-blacksmiths-infuser","name":"Vaal Blacksmith's Infuser","divine":0.2192,"volume":198.2,"change7d":-7.06},{"id":"greater-exalted-orb","name":"Greater Exalted Orb","divine":0.0132,"volume":138.7,"change7d":57.36},{"id":"crystallised-corruption","name":"Crystallised Corruption","divine":2.72,"volume":1481,"change7d":-5.87},{"id":"greater-orb-of-augmentation","name":"Greater Orb of Augmentation","divine":0.0006293,"volume":3.48,"change7d":6.59},{"id":"mirror","name":"Mirror of Kalandra","divine":4681,"volume":127161,"change7d":-11.92},{"id":"artificers-shard","name":"Artificer's Shard","divine":0.001944,"volume":0.03855,"change7d":-85.03},{"id":"greater-regal-orb","name":"Greater Regal Orb","divine":0.005478,"volume":11.55,"change7d":-26.12},{"id":"core-destabiliser","name":"Core Destabiliser","divine":3.83,"volume":3210,"change7d":-23.7},{"id":"hinekoras-lock","name":"Hinekora's Lock","divine":982.0,"volume":39280,"change7d":-29.63},{"id":"chance-shard","name":"Chance Shard","divine":0.001695,"volume":0.03108,"change7d":6.14},{"id":"perfect-orb-of-augmentation","name":"Perfect Orb of Augmentation","divine":0.08878,"volume":830.3,"change7d":42.09},{"id":"lesser-jewellers-orb","name":"Lesser Jeweller's Orb","divine":6.162e-05,"volume":0.1168,"change7d":-41.84},{"id":"transmutation-shard","name":"Transmutation Shard","divine":0.004721,"volume":0.0007868,"change7d":-42.86},{"id":"scrap","name":"Armourer's Scrap","divine":0.006296,"volume":138.5,"change7d":14.0},{"id":"greater-jewellers-orb","name":"Greater Jeweller's Orb","divine":0.002028,"volume":1.97,"change7d":23.24},{"id":"annul","name":"Orb of Annulment","divine":0.5362,"volume":10464,"change7d":-32.83},{"id":"vaal-siphoner","name":"Vaal Siphoner","divine":0.0003106,"volume":0.001967,"change7d":-73.68}]}
